{
  "card_id": "cloth_sprite",
  "species": "cloth_sprite",
  "element": "NORMAL",
  "atk": 4,
  "def": 4,
  "hp": 21,
  "spd": 5,
  "triggers": [
    {
      "when": "ON_TURN_END",
      "op": "HEAL",
      "target": "RANDOM_ALLY",
      "value": 2
    }
  ],
  "name": "Brownie",
  "flavor": "Household helper; he patches the cloak in the night and asks no thanks but the milk.",
  "rarity": "common",
  "archetype": null,
  "canon": "APOCRYPHA",
  "art": "art/common/cloth_sprite.png",
  "moves": []
}
